simple-api-management/__init__.py
simple-api-management/data.py
simple-api-management/middleware.py
simpleapimanagement/__init__.py
simpleapimanagement/data.py
simpleapimanagement/middleware.py
simple_api_management_wsgi-0.2.0.dist-info/LICENSE.md
simple_api_management_wsgi-0.2.0.dist-info/METADATA
simple_api_management_wsgi-0.2.0.dist-info/WHEEL
simple_api_management_wsgi-0.2.0.dist-info/top_level.txt
simple_api_management_wsgi-0.2.0.dist-info/RECORD
