Metadata-Version: 2.1
Name: simple-api-management-wsgi
Version: 0.2.0
Summary: UNKNOWN
Home-page: https://simpleapimanagement.com
Author: Simple API Management
Author-email: sascha@simpleapimanagement.com
License: Apache Software License
Keywords: api management middleware metrics rate limits log analysis restful api development debug wsgi flask bottle http
Platform: UNKNOWN
Classifier: Intended Audience :: Developers
Classifier: Programming Language :: Python :: 2
Classifier: Programming Language :: Python :: 3
Classifier: License :: OSI Approved :: Apache Software License
Classifier: Operating System :: OS Independent
